P2/mux2_1.v
module mux2_1 #(parameter WIDTH = 8)(
    output wire [WIDTH-1:0] y, // Salida
    input [WIDTH-1:0] a, b,    // Entradas
    input sel                  // Señal de selección
);

    assign y = sel ? b : a;

endmodule

P2/ff.v
module ff(output reg q, input d, clk, we);

    always @(posedge clk) begin
        if (we)
            q <= d; // Actualizar el valor de `z` cuando `we` está habilitado
    end

endmodule

P2/alu.v
module alu(
    output reg [7:0] res, // Resultado de la operación
    output reg z,         // Flag de cero
    input [7:0] a, b,     // Operandos
    input [2:0] op        // Código de operación
);

    always @(*) begin
        case (op)
            3'b000: res = a + b;  // Suma
            3'b001: res = a - b;  // Resta
            3'b010: res = a & b;  // AND
            3'b011: res = a | b;  // OR
            3'b100: res = a ^ b;  // XOR
            3'b101: res = ~a;     // NOT
            default: res = 8'b0;  // Operación no válida
        endcase

        // Actualizar el flag de cero
        z = (res == 8'b0);
    end

endmodule

P2/regfile.v
module regfile(
    output reg [7:0] rd1, rd2, // Salidas de lectura
    input clk, we,            // Señal de escritura habilitada
    input [3:0] ra1, ra2, wa3, // Direcciones de lectura y escritura
    input [7:0] wd3            // Datos de entrada para escritura
);

    reg [7:0] regs [0:15]; // Banco de registros: 16 registros de 8 bits

    // Operaciones de lectura
    always @(*) begin
        rd1 = regs[ra1];
        rd2 = regs[ra2];
    end

    // Operación de escritura
    always @(posedge clk) begin
        if (we) begin
            regs[wa3] <= wd3;
        end
    end

endmodule

P2/memprog.v
module memprog(input [9:0] addr, output reg [15:0] data);

    // Memoria de programa
    reg [15:0] rom [0:1023];

    initial begin
        // Cargar el contenido desde un archivo (progfile.dat)
        $readmemh("progfile.dat", rom);
    end

    always @(*) begin
        data = rom[addr]; // Leer la instrucción en la dirección `addr`
    end

endmodule

P2/reg10.v
module reg10(output reg [9:0] q, input [9:0] d, input clk, reset);

    always @(posedge clk or posedge reset) begin
        if (reset)
            q <= 10'b0; // Reinicia el PC a 0
        else
            q <= d; // Carga el nuevo valor del PC
    end

endmodule

P2/microc.v
module microc(
    output wire [5:0] Opcode,
    output wire z,
    input wire clk, reset,
    input wire s_inc, s_inm, we3, wez,
    input wire [2:0] Op
);

    // Señales internas
    wire [9:0] pc_in, pc_out;               // Señales para el PC
    wire [15:0] instr;                      // Instrucción desde la memoria
    wire [7:0] rd1, rd2, alu_out, imm, wd3; // Datos intermedios
    wire z_next;                            // Próximo valor del flag `z`

    // Instancia del Contador de Programa (PC)
    reg10 pc (pc_out, pc_in, clk, reset); // Salida `pc_out`, Entrada `pc_in`

    // Instancia de la Memoria de Programa
    memprog mem (pc_out, instr); // Dirección `pc_out`, Salida `instr`

    // Instancia del Banco de Registros
    regfile banco_registros (
        rd1, rd2,       // Salidas `rd1` y `rd2`
        clk, we3,       // Señales de reloj y escritura
        instr[11:8],    // Dirección de lectura 1 (RA1)
        instr[7:4],     // Dirección de lectura 2 (RA2)
        instr[3:0],     // Dirección de escritura (WA3)
        wd3             // Datos de entrada para escritura
    );

    // Instancia de la ALU
    alu alu_inst (
        alu_out, z_next, // Resultado y flag `z`
        rd1, rd2,        // Operandos `rd1` y `rd2`
        Op               // Operación
    );

    // Instancia del Flip-Flop del Flag de Cero
    ff zero_flag (z, z_next, clk, wez); // Salida `z`, Entrada `z_next`

    // Instancia del Multiplexor para el PC
    mux2_1 #(10) mux_pc (
        pc_in,         // Salida del mux
        pc_out + 1,    // Entrada 0: PC + 1
        instr[9:0],    // Entrada 1: Dirección de salto
        s_inc          // Señal de selección
    );

    // Instancia del Multiplexor para la Entrada del Banco de Registros
    mux2_1 #(8) mux_wd3 (
        wd3,          // Salida del mux
        alu_out,      // Entrada 0: Salida de la ALU
        instr[11:4],  // Entrada 1: Valor inmediato
        s_inm         // Señal de selección
    );

    // Extraer el Opcode de la instrucción
    assign Opcode = instr[15:10];

endmodule

P2/microc_tb_old.v
`timescale 1ns / 10ps
module microc_tb;
// declaracion de variables
reg t_wez, t_we, t_s_inc, t_s_inm, t_clk, t_reset;
reg [2:0] t_ALUOp;
wire [5:0] t_Opcode;
wire t_zero;

// instanciacion del camino de datos
microc microc(t_Opcode, t_zero, t_clk, t_reset, t_s_inc, t_s_inm, t_we, t_wez, t_ALUOp);

// generación de reloj clk
always
begin
    t_clk = 1;
    #15;
    t_clk = 0;
    #15;
end

// Reseteo y configuracion de salidas del testbench
initial
begin
    $dumpfile("cpu_tb.vcd");
    $dumpvars;
    // ... señal de reset
    t_reset = 1;
    #5
    t_reset = 0;
end

// bloque de simulacion señales control por ciclo
initial
begin
    // CICLO 0 LI #3 R3
    #15
    t_wez = 1'b0;
    t_we = 1'b1;
    t_s_inm = 1'b1;
    t_s_inc = 1'b1;
    t_ALUOp = 3'b000;
    #30

    // CICLO 1 LI #1 R5
    t_wez = 1'b0;
    t_we = 1'b1;
    t_s_inm = 1'b1;
    t_s_inc = 1'b1;
    t_ALUOp = 3'b000;
    #30

    // CICLO 2 SUB R2 R2 R2
    t_wez = 1;
    t_we = 1;
    t_s_inm = 0;
    t_s_inc = 1;
    t_ALUOp = 3'b011;
    #30

    // CICLO 3 MOV R3 R4 -> ADD R0 R3 R4
    t_wez = 1;
    t_we = 1;
    t_s_inm = 0;
    t_s_inc = 1;
    t_ALUOp = 3'b010;
    #30

    // CICLO 4 AND R4 R5 R4
    t_wez = 1;
    t_we = 1;
    t_s_inm = 0;
    t_s_inc = 1;
    t_ALUOp = 3'b100;
    #30

    // CICLO 5 SBI #1 R3
    t_wez = 1;
    t_we = 1;
    t_s_inm = 1;
    t_s_inc = 1;
    t_ALUOp = 3'b011;
    #30

    // CICLO 9 J CHECK
    t_wez = 0;
    t_we = 0;
    t_s_inm = 0;
    t_s_inc = 0;
    t_ALUOp = 3'b000;
    #30

    // CICLO 10 MOV R3 R4 -> ADD R0 R3 R4
    t_wez = 1;
    t_we = 1;
    t_s_inm = 0;
    t_s_inc = 1;
    t_ALUOp = 3'b010;
    #30

    // CICLO 11  AND R4 R5 R4
    t_wez = 1;
    t_we = 1;
    t_s_inm = 0;
    t_s_inc = 1;
    t_ALUOp = 3'b100;
    #30

    // CICLO 12 JZ PAR
    t_wez = 0;
    t_we = 0;
    t_s_inm = 0;
    t_s_inc = t_zero;
    t_ALUOp = 3'b000;
    #30

    // CICLO 13 ADI #1 R2
    t_wez = 1;
    t_we = 1;
    t_s_inm = 1;
    t_s_inc = 1;
    t_ALUOp = 3'b010;
    #30

    // CICLO 14 J NEXT
    t_wez = 0;
    t_we = 0;
    t_s_inm = 0;
    t_s_inc = 0;
    t_ALUOp = 3'b000;
    #30
    // CICLO 15 SBI #1 R3
    t_wez = 1;
    t_we = 1;
    t_s_inm = 1;
    t_s_inc = 1;
    t_ALUOp = 3'b011;
    #30

    // CICLO 16 J CHECK
    t_wez = 0;
    t_we = 0;
    t_s_inm = 0;
    t_s_inc = 0;
    t_ALUOp = 3'b000;
    #30

    // CICLO 17 MOV R3 R4 -> ADD R0 R3 R4
    t_wez = 1;
    t_we = 1;
    t_s_inm = 0;
    t_s_inc = 1;
    t_ALUOp = 3'b010;
    #30

    // CICLO 18  AND R4 R5 R4
    t_wez = 1;
    t_we = 1;
    t_s_inm = 0;
    t_s_inc = 1;
    t_ALUOp = 3'b100;
    #30

    // CICLO 19 SBI #1 R3
    t_wez = 1;
    t_we = 1;
    t_s_inm = 1;
    t_s_inc = 1;
    t_ALUOp = 3'b011;
    #30

    // CICLO 20 JZ END
    t_wez = 0;
    t_we = 0;
    t_s_inm = 0;
    t_s_inc = t_zero;
    t_ALUOp = 3'b000;
    #30

    // CICLO 21 J END
    t_wez = 0;
    t_we = 0;
    t_s_inm = 0;
    t_s_inc = 0;
    t_ALUOp = 3'b000;
    #30

    // CICLO 22 J END
    t_wez = 0;
    t_we = 0;
    t_s_inm = 0;
    t_s_inc = 0;
    t_ALUOp = 3'b000;
    #30

    $finish;
end
endmodule

P2/cpu_tb.vcd
$date
	Tue Nov 19 20:48:46 2024
$end
$version
	Icarus Verilog
$end
$timescale
	10ps
$end
$scope module microc_tb $end
$var wire 1 ! t_zero $end
$var wire 6 " t_Opcode [5:0] $end
$var reg 3 # t_ALUOp [2:0] $end
$var reg 1 $ t_clk $end
$var reg 1 % t_reset $end
$var reg 1 & t_s_inc $end
$var reg 1 ' t_s_inm $end
$var reg 1 ( t_we $end
$var reg 1 ) t_wez $end
$scope module microc $end
$var wire 3 * Op [2:0] $end
$var wire 1 $ clk $end
$var wire 1 % reset $end
$var wire 1 & s_inc $end
$var wire 1 ' s_inm $end
$var wire 1 ( we3 $end
$var wire 1 ) wez $end
$var wire 1 + z_next $end
$var wire 1 ! z $end
$var wire 8 , wd3 [7:0] $end
$var wire 8 - rd2 [7:0] $end
$var wire 8 . rd1 [7:0] $end
$var wire 10 / pc_out [9:0] $end
$var wire 10 0 pc_in [9:0] $end
$var wire 16 1 instr [15:0] $end
$var wire 8 2 alu_out [7:0] $end
$var wire 6 3 Opcode [5:0] $end
$scope module alu_inst $end
$var wire 3 4 op [2:0] $end
$var wire 8 5 b [7:0] $end
$var wire 8 6 a [7:0] $end
$var reg 8 7 res [7:0] $end
$var reg 1 + z $end
$upscope $end
$scope module banco_registros $end
$var wire 1 $ clk $end
$var wire 4 8 ra1 [3:0] $end
$var wire 4 9 ra2 [3:0] $end
$var wire 4 : wa3 [3:0] $end
$var wire 1 ( we $end
$var wire 8 ; wd3 [7:0] $end
$var reg 8 < rd1 [7:0] $end
$var reg 8 = rd2 [7:0] $end
$upscope $end
$scope module mem $end
$var wire 10 > addr [9:0] $end
$var reg 16 ? data [15:0] $end
$upscope $end
$scope module mux_pc $end
$var wire 10 @ a [9:0] $end
$var wire 10 A b [9:0] $end
$var wire 1 & sel $end
$var wire 10 B y [9:0] $end
$upscope $end
$scope module mux_wd3 $end
$var wire 8 C a [7:0] $end
$var wire 8 D b [7:0] $end
$var wire 1 ' sel $end
$var wire 8 E y [7:0] $end
$upscope $end
$scope module pc $end
$var wire 1 $ clk $end
$var wire 10 F d [9:0] $end
$var wire 1 % reset $end
$var reg 10 G q [9:0] $end
$upscope $end
$scope module zero_flag $end
$var wire 1 $ clk $end
$var wire 1 + d $end
$var wire 1 ) we $end
$var reg 1 ! q $end
$upscope $end
$upscope $end
$upscope $end
$enddefinitions $end
#0
$dumpvars
b0 G
b0x00000001 F
bx E
b10000 D
bx C
b0x00000001 B
b100000001 A
b1 @
b100000001 ?
b0 >
bx =
bx <
bx ;
b1 :
b0 9
b1 8
bx 7
bx 6
bx 5
bx 4
b0 3
bx 2
b100000001 1
b0x00000001 0
b0 /
bx .
bx -
bx ,
x+
bx *
x)
x(
x'
x&
1%
1$
bx #
b0 "
x!
$end
#500
0%
#1500
b100000001 0
b100000001 B
b100000001 F
b10000 ,
b10000 ;
b10000 E
b0 #
b0 *
b0 4
1&
1'
1(
0)
0$
#3000
b0 ,
b0 ;
b0 E
b0 0
b0 B
b0 F
b0 D
b0 A
b0 :
b0 8
bx .
bx 6
bx <
b100000010 @
b0 1
b0 ?
b100000001 /
b100000001 >
b100000001 G
1$
#4500
0$
#6000
b10000 ,
b10000 ;
b10000 E
b100000001 0
b100000001 B
b100000001 F
0+
b10000 2
b10000 7
b10000 C
b10000 D
b100000001 A
b1 :
b1 8
b0 -
b0 5
b0 =
b10000 .
b10000 6
b10000 <
b1 @
b100000001 1
b100000001 ?
b0 /
b0 >
b0 G
1$
#7500
0$
b11 #
b11 *
b11 4
0'
1)
#9000
b0 ,
b0 ;
b0 E
1+
b0 2
b0 7
b0 C
b0 0
b0 B
b0 F
b0 .
b0 6
b0 <
b0 D
b0 A
b0 :
b0 8
b100000010 @
b0 1
b0 ?
0!
b100000001 /
b100000001 >
b100000001 G
1$
#10500
0$
b10 #
b10 *
b10 4
#12000
b100000001 0
b100000001 B
b100000001 F
b10000 .
b10000 6
b10000 <
b10000 D
b100000001 A
b1 :
b1 8
b1 @
b100000001 1
b100000001 ?
1!
b0 /
b0 >
b0 G
1$
#13500
b10000 ,
b10000 ;
b10000 E
0+
b10000 2
b10000 7
b10000 C
0$
b100 #
b100 *
b100 4
#15000
b0 ,
b0 ;
b0 E
1+
b0 2
b0 7
b0 C
b0 0
b0 B
b0 F
b0 .
b0 6
b0 <
b0 D
b0 A
b0 :
b0 8
b100000010 @
b0 1
b0 ?
0!
b100000001 /
b100000001 >
b100000001 G
1$
#16500
0$
b11 #
b11 *
b11 4
1'
#18000
0+
b10000 2
b10000 7
b10000 C
b10000 ,
b10000 ;
b10000 E
b100000001 0
b100000001 B
b100000001 F
b10000 .
b10000 6
b10000 <
b10000 D
b100000001 A
b1 :
b1 8
b1 @
b100000001 1
b100000001 ?
1!
b0 /
b0 >
b0 G
1$
#19500
b1 0
b1 B
b1 F
0$
b0 #
b0 *
b0 4
0&
0'
0(
0)
#21000
b0 ,
b0 ;
b0 E
1+
b0 2
b0 7
b0 C
b0 .
b0 6
b0 <
b10 0
b10 B
b10 F
b0 D
b0 A
b0 :
b0 8
b10 @
b0 1
b0 ?
b1 /
b1 >
b1 G
1$
#22500
b0 0
b0 B
b0 F
0$
b10 #
b10 *
b10 4
1&
1(
1)
#24000
b100000001 0
b100000001 B
b100000001 F
b10000 .
b10000 6
b10000 <
b10000 D
b100000001 A
b1 :
b1 8
b1 @
b100000001 1
b100000001 ?
b0 /
b0 >
b0 G
1$
#25500
b10000 ,
b10000 ;
b10000 E
0+
b10000 2
b10000 7
b10000 C
0$
b100 #
b100 *
b100 4
#27000
b0 ,
b0 ;
b0 E
1+
b0 2
b0 7
b0 C
b0 0
b0 B
b0 F
b0 .
b0 6
b0 <
b0 D
b0 A
b0 :
b0 8
b100000010 @
b0 1
b0 ?
0!
b100000001 /
b100000001 >
b100000001 G
1$
#28500
b100000010 0
b100000010 B
b100000010 F
0$
b0 #
b0 *
b0 4
0&
0(
0)
#30000
b100000011 0
b100000011 B
b100000011 F
b100000011 @
b100000010 /
b100000010 >
b100000010 G
1$
#31500
b0 0
b0 B
b0 F
0$
b10 #
b10 *
b10 4
1&
1'
1(
1)
#33000
b10000 ,
b10000 ;
b10000 E
b100000001 0
b100000001 B
b100000001 F
b10000 .
b10000 6
b10000 <
b10000 D
b100000001 A
b1 :
b1 8
b1 @
b100000001 1
b100000001 ?
1!
b0 /
b0 >
b0 G
1$
#34500
0+
b10000 2
b10000 7
b10000 C
b1 0
b1 B
b1 F
b10000 ,
b10000 ;
b10000 E
0$
b0 #
b0 *
b0 4
0&
0'
0(
0)
#36000
b0 ,
b0 ;
b0 E
1+
b0 2
b0 7
b0 C
b0 .
b0 6
b0 <
b10 0
b10 B
b10 F
b0 D
b0 A
b0 :
b0 8
b10 @
b0 1
b0 ?
b1 /
b1 >
b1 G
1$
#37500
b0 0
b0 B
b0 F
0$
b11 #
b11 *
b11 4
1&
1'
1(
1)
#39000
0+
b10000 2
b10000 7
b10000 C
b10000 ,
b10000 ;
b10000 E
b100000001 0
b100000001 B
b100000001 F
b10000 .
b10000 6
b10000 <
b10000 D
b100000001 A
b1 :
b1 8
b1 @
b100000001 1
b100000001 ?
b0 /
b0 >
b0 G
1$
#40500
b1 0
b1 B
b1 F
0$
b0 #
b0 *
b0 4
0&
0'
0(
0)
#42000
b0 ,
b0 ;
b0 E
1+
b0 2
b0 7
b0 C
b0 .
b0 6
b0 <
b10 0
b10 B
b10 F
b0 D
b0 A
b0 :
b0 8
b10 @
b0 1
b0 ?
b1 /
b1 >
b1 G
1$
#43500
b0 0
b0 B
b0 F
0$
b10 #
b10 *
b10 4
1&
1(
1)
#45000
b100000001 0
b100000001 B
b100000001 F
b10000 .
b10000 6
b10000 <
b10000 D
b100000001 A
b1 :
b1 8
b1 @
b100000001 1
b100000001 ?
b0 /
b0 >
b0 G
1$
#46500
b10000 ,
b10000 ;
b10000 E
0+
b10000 2
b10000 7
b10000 C
0$
b100 #
b100 *
b100 4
#48000
b0 ,
b0 ;
b0 E
1+
b0 2
b0 7
b0 C
b0 0
b0 B
b0 F
b0 .
b0 6
b0 <
b0 D
b0 A
b0 :
b0 8
b100000010 @
b0 1
b0 ?
0!
b100000001 /
b100000001 >
b100000001 G
1$
#49500
0$
b11 #
b11 *
b11 4
1'
#51000
0+
b10000 2
b10000 7
b10000 C
b10000 ,
b10000 ;
b10000 E
b100000001 0
b100000001 B
b100000001 F
b10000 .
b10000 6
b10000 <
b10000 D
b100000001 A
b1 :
b1 8
b1 @
b100000001 1
b100000001 ?
1!
b0 /
b0 >
b0 G
1$
#52500
0$
b0 #
b0 *
b0 4
0'
0(
0)
#54000
b0 ,
b0 ;
b0 E
1+
b0 2
b0 7
b0 C
b0 0
b0 B
b0 F
b0 .
b0 6
b0 <
b0 D
b0 A
b0 :
b0 8
b100000010 @
b0 1
b0 ?
b100000001 /
b100000001 >
b100000001 G
1$
#55500
b100000010 0
b100000010 B
b100000010 F
0$
0&
#57000
b100000011 0
b100000011 B
b100000011 F
b100000011 @
b100000010 /
b100000010 >
b100000010 G
1$
#58500
0$
#60000
b100000100 0
b100000100 B
b100000100 F
b100000100 @
b100000011 /
b100000011 >
b100000011 G
1$
