P2_VERDADERA/componentes.v
//Componentes varios

// Banco de registros de dos salidas y una entrada
module regfile(output wire [7:0]  RD1, RD2,     //datos leidos
               input  wire        clk,          // Señal de reloj
               input  wire        we3,          //señal de habilitación de escritura
               input  wire [3:0]  RA1, RA2, WA3,//direcciones de regs leidos y reg a escribir
               input  wire [7:0]  WD3);         //dato a escribir

  reg [7:0] R[0:15]; //memoria de 32 registros de 8 bits de ancho

  initial
  begin
    $readmemb("regfile.dat", R); // inicializa los registros a valores conocidos
  end  
  
  // El registro 0 siempre es cero
  // se leen dos reg combinacionalmente
  // y la escritura del tercero ocurre en flanco de subida del reloj
  always @(posedge clk)
    if (we3) R[WA3] <= WD3;	
  
  assign RD1 = (RA1 != 0) ? R[RA1] : 0;
  assign RD2 = (RA2 != 0) ? R[RA2] : 0;
endmodule

// Sumador simple
module sum(output wire [9:0] Y,     // Salida del sumador
           input  wire [9:0] A, B); // Operandos de la suma

  assign Y = A + B;
endmodule

// Registro de tamaño configurable para modelar el PC. Cambia en cada flanco de subida de reloj o de reset
module registro #(parameter WIDTH = 8)
              (output reg  [WIDTH-1:0] Q,           // Salida del registro
               input  wire             clk, reset,  // Señales de reloj y reseteo
               input  wire [WIDTH-1:0] D);          // Entrada al registro

  always @(posedge clk, posedge reset)
    if (reset) Q <= 0;
    else       Q <= D;
endmodule

// Multiplexor de dos entradas y una salida, de tamaño configurable. Si la señal de selección "s" vale 1, se pone el valor de d1 en la salida; d0 si vale 0
module mux2 #(parameter WIDTH = 8)
             (output wire [WIDTH-1:0] Y,      // Salida del multiplexor
              input  wire [WIDTH-1:0] D0, D1, // Entradas del multiplexor
              input  wire             s);     // Selección

  assign Y = s ? D1 : D0; 
endmodule

//Biestable para el flag de cero
//Biestable tipo D síncrono con reset asíncrono por flanco y entrada de habilitación de carga
module ffd(input wire clk, reset, d, carga, output reg q);
  always @(posedge clk, posedge reset)
    if (reset)
	    q <= 1'b0;
	  else
	    if (carga)
	      q <= d;
endmodule

P2_VERDADERA/alu.v
module alu(output reg [7:0] S,    // Salida de la ALU
           output reg zero,       // Flag de cero
           input wire [7:0] A, B, // Operandos
           input wire [2:0] Op    // Elección de operación a realizar
           );
// Una ALU simple que puede realizar 8 operaciones diferentes, y que devuelve el resultado, además de flags de cero y acarreo
	   
always @(A, B, Op)
begin
  case (Op)              
    3'b000: S = A; 
    3'b001: S = ~A;
    3'b010: S = A + B;
    3'b011: S = A - B;
    3'b100: S = A & B;
    3'b101: S = A | B;
    3'b110: S = -A;
    3'b111: S = -B;
	  default: S = 'bx; //desconocido en cualquier otro caso (x | z), por si se modifica el código
  endcase
  //Calculo del flag de cero
  zero = ~(|S);   //operador de reducción |y hace la or de los bits del vector 'y' y devuelve 1 bit resultado
end
	   
endmodule

P2_VERDADERA/memprog.v
//Memoria de programa, se inicializa y no se modifica

module memprog(output wire [15:0] Data,     // Dato que se lee de memoria
               input  wire clk,             // Señal de reloj
               input  wire [9:0] Address);  // Dirección de memoria a la que se accede

  reg [15:0] Mem[0:1023]; //memoria de 1024 palabras de 16 bits de ancho

  initial
  begin
    $readmemb("progfile.dat", Mem); // inicializa la memoria del fichero en texto binario
  end
  assign Data = Mem[Address];
endmodule

P2_VERDADERA/microc.v
module microc(output wire [5:0] Opcode, output wire z, input wire clk, reset, s_inc, s_inm, we3, wez, input wire [2:0] Op);
//Microcontrolador sin memoria de datos de un solo ciclo
 // Señales internas
    wire [9:0] pc_in, pc_out, sum_out;                  // Señales para el PC
    wire [15:0] instr;                                  // Instrucción desde la memoria
    wire [7:0] rd1, rd2, alu_out, imm, wd3, mux2_out;   // Datos intermedios
    wire z_next;                                        // Próximo valor del flag `z`
    wire [3:0] mux1_out;                                // Datos intermedios

    // Instancia del Contador de Programa (PC)
    registro #(10) pc (pc_out, clk, reset, pc_in); // Salida `pc_out`, Entrada `pc_in`

    // Sumador simple
    sum sumador(sum_out, pc_out, 10'b1);

    // Multiplexor PC
    mux2 #(10) mux_pc (pc_in, sum_out, instr[9:0], s_inc); 

    // Instancia de la Memoria de Programa
    memprog mem (instr, clk, pc_out); // Dirección `pc_out`, Salida `instr`

    // Instancia del Banco de Registros
    regfile banco_registros (
        rd1, rd2,       // Salidas `rd1` y `rd2`
        clk, we3,       // Señales de reloj y escritura
        instr[11:8],    // Dirección de lectura 1 (RA1)
        mux1_out,       // Dirección de lectura 2 Salida mux
        instr[3:0],     // Dirección de escritura (WA3)
        wd3             // Datos de entrada para escritura
    );

    // Instancia de la ALU
    alu alu_inst (
        wd3, z_next, // Resultado y flag `z`
        mux2_out, rd2,        // Operandos `rd1` y `rd2`
        Op               // Operación
    );

    // Instancia del Flip-Flop del Flag de Cero
    ffd zero_flag (z, z_next, clk, wez, reset); // Salida `z`, Entrada `z_next`

    // Instancia del Multiplexor para el Banco de Registros
    mux2 #(4) mux_bc (
        mux1_out,         // Salida del mux
       instr[7:4],    // Entrada 0: RA2
        instr[3:0],    // Entrada 1: WA3
        s_inm          // Señal de selección
    );

    // Instancia del Multiplexor para la Entrada de la ALU
    mux2 #(8) mux_alu (
        mux2_out,         // Salida del mux
        rd1,      // Entrada 0: rd1
        s_inm             // Señal de selección
    );

    // Extraer el Opcode de la instrucción
    assign Opcode = instr[15:10];

endmodule

P2_VERDADERA/microc_tb.v
`timescale 1 ns / 10 ps
module microc_tb;

 // Declaración de señales
    reg t_clk, t_reset;
    reg t_s_inc, t_s_inm, t_we, t_wez;
    reg [2:0] t_ALUOp;
    wire [5:0] Opcode;
    wire z;

    // Instancia del módulo microc
    microc uut (
        Opcode,  // Salida del Opcode
        z,       // Flag de cero
        t_clk,     // Señal de reloj
        t_reset,   // Señal de t_reset
        t_s_inc,   // Señal de selección del multiplexor del PC
        t_s_inm,   // Señal de selección del multiplexor del banco de registros
        t_we,     // Habilitación de escritura del banco de registros
        t_wez,     // Habilitación de escritura del flag de cero
        t_ALUOp       // Código de operación para la ALU
    );

    // Generación del reloj
    always
begin
    t_clk = 1;
    #15;
    t_clk = 0;
    #15;
end

// Reseteo y configuración de salidas del testbench
initial
begin
  $dumpfile("microc_tb.vcd");
  $dumpvars;
  // Inicialización
        t_clk = 0;
        t_reset = 1; 
        t_s_inc = 0; 
        t_s_inm = 0; 
        t_we = 0; 
        t_wez = 0; 
        t_ALUOp = 3'b000;

        #10 t_reset = 0; // Liberar el reset
end

// Bloque simulación señales control por ciclo
initial
begin
   // CICLO 0 JMP START
    #15
    t_wez = 1'b0;
    t_we = 1'b0;
    t_s_inm = 1'b0;
    t_s_inc = 1'b0;
    t_ALUOp = 3'b000;
    #30

    // CICLO 1 LI #0 R1
    t_wez = 1'b0;
    t_we = 1'b1;
    t_s_inm = 1'b1;
    t_s_inc = 1'b1;
    t_ALUOp = 3'b000;
    #30

    // CICLO 2 LI #2 R2
    t_wez = 1'b0;
    t_we = 1'b1;
    t_s_inm = 1'b1;
    t_s_inc = 1'b1;
    t_ALUOp = 3'b000;
    #30

    // CICLO 3 LI #3 R3
    t_wez = 1'b0;
    t_we = 1'b1;
    t_s_inm = 1'b1;
    t_s_inc = 1'b1;
    t_ALUOp = 3'b000;
    #30

    // CICLO 4 sub R1 R2 R0 
    t_wez = 1;
    t_we = 1;
    t_s_inm = 0;
    t_s_inc = 1;
    t_ALUOp = 3'b011;
    #30

    // CICLO 5 jnz Fin
    t_wez = 1;
    t_we = 0;
    t_s_inm = 0;
    t_s_inc = 1;
    t_ALUOp = 3'b000;
    #30

    // CICLO 6 add R3 R3 R3
    t_wez = 1;
    t_we = 1;
    t_s_inm = 0;
    t_s_inc = 1;
    t_ALUOp = 3'b010;
    #30

    // CICLO 7 addi 1 R1
    t_wez = 1;
    t_we = 1;
    t_s_inm = 1;
    t_s_inc = 1;
    t_ALUOp = 3'b010;
    #30

    // CICLO 8 nop
    //t_wez = 0;
    //t_we = 0;
    //t_s_inm = 0;
    //t_s_inc = 0;
    //t_ALUOp = 3'b000;
    //#30

    // CICLO 9  j Test
    t_wez = 1'b0;
    t_we = 1'b0;
    t_s_inm = 1'b0;
    t_s_inc = 1'b0;
    t_ALUOp = 3'b000;
    #30

    // CICLO 10 sub R1 R2 R0 
    t_wez = 1;
    t_we = 1;
    t_s_inm = 0;
    t_s_inc = 1;
    t_ALUOp = 3'b011;
    #30

    // CICLO 11 jnz Fin
    t_wez = 1;
    t_we = 0;
    t_s_inm = 0;
    t_s_inc = 1;
    t_ALUOp = 3'b000;
    #30

    // CICLO 12 add R3 R3 R3
    t_wez = 1;
    t_we = 1;
    t_s_inm = 0;
    t_s_inc = 1;
    t_ALUOp = 3'b010;
    #30

    // CICLO 13 addi 1 R1
    t_wez = 1;
    t_we = 1;
    t_s_inm = 1;
    t_s_inc = 1;
    t_ALUOp = 3'b010;
    #30

    // CICLO 14 nop
    t_wez = 1;
    t_we = 1;
    t_s_inm = 0;
    t_s_inc = 1;
    t_ALUOp = 3'b010;
    #30

    // CICLO 15  j Test
    t_wez = 1;
    t_we = 1;
    t_s_inm = 0;
    t_s_inc = 1;
    t_ALUOp = 3'b100;
    #30

    // CICLO 16 sub R1 R2 R0 
    t_wez = 1;
    t_we = 1;
    t_s_inm = 0;
    t_s_inc = 1;
    t_ALUOp = 3'b011;
    #30

    // CICLO 17 jnz Fin *
    t_wez = 1;
    t_we = 0;
    t_s_inm = 0;
    t_s_inc = 0;
    t_ALUOp = 3'b000;
    #30

    // CICLO 18 j Fin
    t_wez = 1'b0;
    t_we = 1'b0;
    t_s_inm = 1'b0;
    t_s_inc = 1'b0;
    t_ALUOp = 3'b000;
    #30

    // CICLO 19 j Fin
    t_wez = 1'b0;
    t_we = 1'b0;
    t_s_inm = 1'b0;
    t_s_inc = 1'b0;
    t_ALUOp = 3'b000;
    #30
  $finish;
end

endmodule

P2_VERDADERA/microc_tb.vcd
$date
	Wed Nov 20 18:38:39 2024
$end
$version
	Icarus Verilog
$end
$timescale
	10ps
$end
$scope module microc_tb $end
$var wire 1 ! z $end
$var wire 6 " Opcode [5:0] $end
$var reg 3 # t_ALUOp [2:0] $end
$var reg 1 $ t_clk $end
$var reg 1 % t_reset $end
$var reg 1 & t_s_inc $end
$var reg 1 ' t_s_inm $end
$var reg 1 ( t_we $end
$var reg 1 ) t_wez $end
$scope module uut $end
$var wire 3 * Op [2:0] $end
$var wire 1 $ clk $end
$var wire 16 + instr [15:0] $end
$var wire 10 , pc_out [9:0] $end
$var wire 1 - reset $end
$var wire 1 & s_inc $end
$var wire 1 ' s_inm $end
$var wire 1 ( we3 $end
$var wire 1 ) wez $end
$var wire 1 ! z $end
$var wire 1 . z_next $end
$var wire 8 / wd3 [7:0] $end
$var wire 10 0 sum_out [9:0] $end
$var wire 8 1 rd2 [7:0] $end
$var wire 8 2 rd1 [7:0] $end
$var wire 10 3 pc_in [9:0] $end
$var wire 8 4 mux2_out [7:0] $end
$var wire 4 5 mux1_out [3:0] $end
$var wire 6 6 Opcode [5:0] $end
$scope module alu_inst $end
$var wire 8 7 A [7:0] $end
$var wire 3 8 Op [2:0] $end
$var wire 8 9 B [7:0] $end
$var reg 8 : S [7:0] $end
$var reg 1 . zero $end
$upscope $end
$scope module banco_registros $end
$var wire 4 ; RA1 [3:0] $end
$var wire 4 < WA3 [3:0] $end
$var wire 8 = WD3 [7:0] $end
$var wire 1 $ clk $end
$var wire 1 ( we3 $end
$var wire 8 > RD2 [7:0] $end
$var wire 8 ? RD1 [7:0] $end
$var wire 4 @ RA2 [3:0] $end
$upscope $end
$scope module mem $end
$var wire 10 A Address [9:0] $end
$var wire 16 B Data [15:0] $end
$var wire 1 $ clk $end
$upscope $end
$scope module mux_alu $end
$var wire 8 C D0 [7:0] $end
$var wire 8 D D1 [7:0] $end
$var wire 1 ' s $end
$var wire 8 E Y [7:0] $end
$upscope $end
$scope module mux_bc $end
$var wire 4 F D0 [3:0] $end
$var wire 4 G D1 [3:0] $end
$var wire 1 ' s $end
$var wire 4 H Y [3:0] $end
$upscope $end
$scope module mux_pc $end
$var wire 10 I D1 [9:0] $end
$var wire 1 J s $end
$var wire 10 K Y [9:0] $end
$var wire 10 L D0 [9:0] $end
$upscope $end
$scope module pc $end
$var wire 8 M D [7:0] $end
$var wire 1 N clk $end
$var wire 1 $ reset $end
$var reg 8 O Q [7:0] $end
$upscope $end
$scope module sumador $end
$var wire 10 P A [9:0] $end
$var wire 10 Q B [9:0] $end
$var wire 10 R Y [9:0] $end
$upscope $end
$scope module zero_flag $end
$var wire 1 ) carga $end
$var wire 1 ! clk $end
$var wire 1 $ d $end
$var wire 1 . reset $end
$var reg 1 S q $end
$upscope $end
$upscope $end
$upscope $end
$enddefinitions $end
#0
$dumpvars
xS
bx R
b1 Q
bx P
b0x O
xN
b0x M
bx L
bx K
zJ
b0 I
bz H
bz G
bz F
b0zzzz E
bz D
b0zzzz C
bx B
bz A
bz @
bx ?
bx >
bx =
bz <
bz ;
bx :
bx 9
b0z 8
b0z 7
bz 6
bz 5
b0zzzz 4
bx 3
bx 2
bx 1
bx 0
bx /
x.
x-
bx ,
bz +
b0z *
0)
0(
0'
0&
1%
0$
b0 #
bz "
z!
$end
#1000
0%
#3000
b0 O
1$
#4500
bz 4
bz E
0$
b1 I
1&
1'
1(
#6000
1$
#7500
0$
#9000
1$
#10500
0$
#12000
1$
#13500
b0zzzz 4
b0zzzz E
0$
b11 #
0'
1)
#15000
1$
#16500
0$
b0 #
0(
#18000
1$
#19500
0$
b10 #
1(
#21000
1$
#22500
bz 4
bz E
0$
1'
#24000
1$
#25500
b0zzzz 4
b0zzzz E
0$
b0 #
b0 I
0&
0'
0(
0)
#27000
1$
#28500
0$
b11 #
b1 I
1&
1(
1)
#30000
1$
#31500
0$
b0 #
0(
#33000
1$
#34500
0$
b10 #
1(
#36000
1$
#37500
bz 4
bz E
0$
1'
#39000
1$
#40500
b0zzzz 4
b0zzzz E
0$
0'
#42000
1$
#43500
0$
b100 #
#45000
1$
#46500
0$
b11 #
#48000
1$
#49500
0$
b0 #
b0 I
0&
0(
#51000
1$
#52500
0$
0)
