P2_VERDADERA/componentes.v
//Componentes varios

// Banco de registros de dos salidas y una entrada
module regfile(output wire [7:0]  RD1, RD2,     //datos leidos
               input  wire        clk,          // Señal de reloj
               input  wire        we3,          //señal de habilitación de escritura
               input  wire [3:0]  RA1, RA2, WA3,//direcciones de regs leidos y reg a escribir
               input  wire [7:0]  WD3);         //dato a escribir

  reg [7:0] R[0:15]; //memoria de 32 registros de 8 bits de ancho

  initial
  begin
    $readmemb("regfile.dat", R); // inicializa los registros a valores conocidos
  end  
  
  // El registro 0 siempre es cero
  // se leen dos reg combinacionalmente
  // y la escritura del tercero ocurre en flanco de subida del reloj
  always @(posedge clk)
    if (we3) R[WA3] <= WD3;	
  
  assign RD1 = (RA1 != 0) ? R[RA1] : 0;
  assign RD2 = (RA2 != 0) ? R[RA2] : 0;
endmodule

// Sumador simple
module sum(output wire [9:0] Y,     // Salida del sumador
           input  wire [9:0] A, B); // Operandos de la suma

  assign Y = A + B;
endmodule

// Registro de tamaño configurable para modelar el PC. Cambia en cada flanco de subida de reloj o de reset
module registro #(parameter WIDTH = 8)
              (output reg  [WIDTH-1:0] Q,           // Salida del registro
               input  wire             clk, reset,  // Señales de reloj y reseteo
               input  wire [WIDTH-1:0] D);          // Entrada al registro

  always @(posedge clk, posedge reset)
    if (reset) Q <= 0;
    else       Q <= D;
endmodule

// Multiplexor de dos entradas y una salida, de tamaño configurable. Si la señal de selección "s" vale 1, se pone el valor de d1 en la salida; d0 si vale 0
module mux2 #(parameter WIDTH = 8)
             (output wire [WIDTH-1:0] Y,      // Salida del multiplexor
              input  wire [WIDTH-1:0] D0, D1, // Entradas del multiplexor
              input  wire             s);     // Selección

  assign Y = s ? D1 : D0; 
endmodule

//Biestable para el flag de cero
//Biestable tipo D síncrono con reset asíncrono por flanco y entrada de habilitación de carga
module ffd(input wire clk, reset, d, carga, output reg q);
  always @(posedge clk, posedge reset)
    if (reset)
	    q <= 1'b0;
	  else
	    if (carga)
	      q <= d;
endmodule

P2_VERDADERA/alu.v
module alu(output reg [7:0] S,    // Salida de la ALU
           output reg zero,       // Flag de cero
           input wire [7:0] A, B, // Operandos
           input wire [2:0] Op    // Elección de operación a realizar
           );
// Una ALU simple que puede realizar 8 operaciones diferentes, y que devuelve el resultado, además de flags de cero y acarreo
	   
always @(A, B, Op)
begin
  case (Op)              
    3'b000: S = A; 
    3'b001: S = ~A;
    3'b010: S = A + B;
    3'b011: S = A - B;
    3'b100: S = A & B;
    3'b101: S = A | B;
    3'b110: S = -A;
    3'b111: S = -B;
	  default: S = 'bx; //desconocido en cualquier otro caso (x | z), por si se modifica el código
  endcase
  //Calculo del flag de cero
  zero = ~(|S);   //operador de reducción |y hace la or de los bits del vector 'y' y devuelve 1 bit resultado
end
	   
endmodule

P2_VERDADERA/memprog.v
//Memoria de programa, se inicializa y no se modifica

module memprog(output wire [15:0] Data,     // Dato que se lee de memoria
               input  wire clk,             // Señal de reloj
               input  wire [9:0] Address);  // Dirección de memoria a la que se accede

  reg [15:0] Mem[0:1023]; //memoria de 1024 palabras de 16 bits de ancho

  initial
  begin
    $readmemb("progfile.dat", Mem); // inicializa la memoria del fichero en texto binario
  end
  assign Data = Mem[Address];
endmodule

P2_VERDADERA/microc.v
module microc(output wire [5:0] Opcode, output wire z, input wire clk, reset, s_inc, s_inm, we3, wez, input wire [2:0] Op);
//Microcontrolador sin memoria de datos de un solo ciclo
 // Señales internas
    wire [9:0] pc_in, pc_out, sum_out;                  // Señales para el PC
    wire [15:0] instr;                                  // Instrucción desde la memoria
    wire [7:0] rd1, rd2, alu_out, imm, wd3, mux2_out;   // Datos intermedios
    wire z_next;                                        // Próximo valor del flag `z`
    wire [3:0] mux1_out;                                // Datos intermedios

    // Instancia del Contador de Programa (PC)
    registro #(10) pc (pc_out, clk, reset, pc_in); // Salida `pc_out`, Entrada `pc_in`

    // Sumador simple
    sum sumador(sum_out, pc_out, 10'b1);

    // Multiplexor PC
    mux2 #(10) mux_pc (pc_in, instr[9:0], sum_out, s_inc); 

    // Instancia de la Memoria de Programa
    memprog mem (instr, clk, pc_out); // Dirección `pc_out`, Salida `instr`

    // Instancia del Banco de Registros
    regfile banco_registros (
        rd1, rd2,       // Salidas `rd1` y `rd2`
        clk, we3,       // Señales de reloj y escritura
        instr[11:8],    // Dirección de lectura 1 (RA1)
        mux1_out,       // Dirección de lectura 2 Salida mux
        instr[3:0],     // Dirección de escritura (WA3)
        wd3             // Datos de entrada para escritura
    );

    // Instancia de la ALU
    alu alu_inst (
        wd3, z_next, // Resultado y flag `z`
        mux2_out, rd2,        // Operandos `rd1` y `rd2`
        Op               // Operación
    );

    // Instancia del Flip-Flop del Flag de Cero
    ffd zero_flag (clk, reset, z_next, wez, z); // Salida `z`, Entrada `z_next`

    // Instancia del Multiplexor para el Banco de Registros
    mux2 #(4) mux_bc (
        mux1_out,         // Salida del mux
       instr[7:4],    // Entrada 0: RA2
        instr[3:0],    // Entrada 1: WA3
        s_inm          // Señal de selección
    );

    // Instancia del Multiplexor para la Entrada de la ALU
    mux2 #(8) mux_alu (
        mux2_out,         // Salida del mux
        rd1,               // Entrada 0: rd1
        instr[11:4],        // inm
        s_inm             // Señal de selección
    );

    // Extraer el Opcode de la instrucción
    assign Opcode = instr[15:10];

endmodule

P2_VERDADERA/microc_tb.v
`timescale 1 ns / 10 ps
module microc_tb;

 // Declaración de señales
    reg t_clk, t_reset;
    reg t_s_inc, t_s_inm, t_we, t_wez;
    reg [2:0] t_ALUOp;
    wire [5:0] Opcode;
    wire z;

    // Instancia del módulo microc
    microc uut (
        Opcode,  // Salida del Opcode
        z,       // Flag de cero
        t_clk,     // Señal de reloj
        t_reset,   // Señal de t_reset
        t_s_inc,   // Señal de selección del multiplexor del PC
        t_s_inm,   // Señal de selección del multiplexor del banco de registros
        t_we,     // Habilitación de escritura del banco de registros
        t_wez,     // Habilitación de escritura del flag de cero
        t_ALUOp       // Código de operación para la ALU
    );

    // Generación del reloj
    always
begin
    t_clk = 1;
    #15;
    t_clk = 0;
    #15;
end

// Reseteo y configuración de salidas del testbench
initial
begin
  $dumpfile("microc_tb.vcd");
  $dumpvars;
  $dumpvars(0, uut.banco_registros.R[1]);
  $dumpvars(0, uut.banco_registros.R[2]);
  $dumpvars(0, uut.banco_registros.R[3]);
  // Inicialización
        t_reset = 1; 

        #5;
        t_reset = 0; // Liberar el reset
end

// Bloque simulación señales control por ciclo
initial
begin
   // CICLO 0 JMP START
    #15;
    t_wez = 1'b0;
    t_we = 1'b0;
    t_s_inm = 1'b0;
    t_s_inc = 1'b0;
    t_ALUOp = 3'b000;
    #30;

    // CICLO 1 LI #0 R1
    t_wez = 1'b0;
    t_we = 1'b1;
    t_s_inm = 1'b1;
    t_s_inc = 1'b1;
    t_ALUOp = 3'b000;
    #30;

    // CICLO 2 LI #2 R2
    t_wez = 1'b0;
    t_we = 1'b1;
    t_s_inm = 1'b1;
    t_s_inc = 1'b1;
    t_ALUOp = 3'b000;
    #30;

    // CICLO 3 LI #3 R3
    t_wez = 1'b0;
    t_we = 1'b1;
    t_s_inm = 1'b1;
    t_s_inc = 1'b1;
    t_ALUOp = 3'b000;
    #30;

    // CICLO 4 sub R1 R2 R0 
    t_wez = 1;
    t_we = 1;
    t_s_inm = 0;
    t_s_inc = 1;
    t_ALUOp = 3'b011;
    #30;

    // CICLO 5 jnz Fin
    t_wez = 1;
    t_we = 0;
    t_s_inm = 0;
    t_s_inc = 1;
    t_ALUOp = 3'b000;
    #30;

    // CICLO 6 add R3 R3 R3
    t_wez = 1;
    t_we = 1;
    t_s_inm = 0;
    t_s_inc = 1;
    t_ALUOp = 3'b010;
    #30;

    // CICLO 7 addi 1 R1
    t_wez = 1;
    t_we = 1;
    t_s_inm = 1;
    t_s_inc = 1;
    t_ALUOp = 3'b010;
    #30;

    // CICLO 8 nop
    t_wez = 0;
    t_we = 0;
    t_s_inm = 0;
    t_s_inc = 1;
    t_ALUOp = 3'b000;
    #30;

    // CICLO 9  j Test
    t_wez = 1'b0;
    t_we = 1'b0;
    t_s_inm = 1'b0;
    t_s_inc = 1'b0;
    t_ALUOp = 3'b000;
    #30;

    // CICLO 10 sub R1 R2 R0 
    t_wez = 1;
    t_we = 1;
    t_s_inm = 0;
    t_s_inc = 1;
    t_ALUOp = 3'b011;
    #30;

    // CICLO 11 jnz Fin
    t_wez = 1;
    t_we = 0;
    t_s_inm = 0;
    t_s_inc = 1;
    t_ALUOp = 3'b000;
    #30;

    // CICLO 12 add R3 R3 R3
    t_wez = 1;
    t_we = 1;
    t_s_inm = 0;
    t_s_inc = 1;
    t_ALUOp = 3'b010;
    #30;

    // CICLO 13 addi 1 R1
    t_wez = 1;
    t_we = 1;
    t_s_inm = 1;
    t_s_inc = 1;
    t_ALUOp = 3'b010;
    #30;

    // CICLO 14 nop
    t_wez = 0;
    t_we = 0;
    t_s_inm = 0;
    t_s_inc = 1;
    t_ALUOp = 3'b000;
    #30;

    // CICLO 15  j Test
    t_wez = 0;
    t_we = 0;
    t_s_inm = 0;
    t_s_inc = 0;
    t_ALUOp = 3'b000;
    #30;

    // CICLO 16 sub R1 R2 R0 
    t_wez = 1;
    t_we = 1;
    t_s_inm = 0;
    t_s_inc = 1;
    t_ALUOp = 3'b011;
    #30;

    // CICLO 17 jnz Fin *
    t_wez = 1;
    t_we = 0;
    t_s_inm = 0;
    t_s_inc = 0;
    t_ALUOp = 3'b000;
    #30;

    // CICLO 18 j Fin
    t_wez = 1'b0;
    t_we = 1'b0;
    t_s_inm = 1'b0;
    t_s_inc = 0;
    t_ALUOp = 3'b000;
    #30;

    // CICLO 19 j Fin
    t_wez = 1'b0;
    t_we = 1'b0;
    t_s_inm = 1'b0;
    t_s_inc = 0;
    t_ALUOp = 3'b000;
    #30;
  $finish;
end

endmodule

P2_VERDADERA/microc_tb.vcd
$date
	Wed Nov 20 20:25:57 2024
$end
$version
	Icarus Verilog
$end
$timescale
	10ps
$end
$scope module microc_tb $end
$var wire 1 ! z $end
$var wire 6 " Opcode [5:0] $end
$var reg 3 # t_ALUOp [2:0] $end
$var reg 1 $ t_clk $end
$var reg 1 % t_reset $end
$var reg 1 & t_s_inc $end
$var reg 1 ' t_s_inm $end
$var reg 1 ( t_we $end
$var reg 1 ) t_wez $end
$scope module uut $end
$var wire 3 * Op [2:0] $end
$var wire 1 $ clk $end
$var wire 1 % reset $end
$var wire 1 & s_inc $end
$var wire 1 ' s_inm $end
$var wire 1 ( we3 $end
$var wire 1 ) wez $end
$var wire 1 + z_next $end
$var wire 1 ! z $end
$var wire 8 , wd3 [7:0] $end
$var wire 10 - sum_out [9:0] $end
$var wire 8 . rd2 [7:0] $end
$var wire 8 / rd1 [7:0] $end
$var wire 10 0 pc_out [9:0] $end
$var wire 10 1 pc_in [9:0] $end
$var wire 8 2 mux2_out [7:0] $end
$var wire 4 3 mux1_out [3:0] $end
$var wire 16 4 instr [15:0] $end
$var wire 6 5 Opcode [5:0] $end
$scope module alu_inst $end
$var wire 3 6 Op [2:0] $end
$var wire 8 7 B [7:0] $end
$var wire 8 8 A [7:0] $end
$var reg 8 9 S [7:0] $end
$var reg 1 + zero $end
$upscope $end
$scope module banco_registros $end
$var wire 4 : RA1 [3:0] $end
$var wire 4 ; WA3 [3:0] $end
$var wire 8 < WD3 [7:0] $end
$var wire 1 $ clk $end
$var wire 1 ( we3 $end
$var wire 8 = RD2 [7:0] $end
$var wire 8 > RD1 [7:0] $end
$var wire 4 ? RA2 [3:0] $end
$upscope $end
$scope module mem $end
$var wire 16 @ Data [15:0] $end
$var wire 1 $ clk $end
$var wire 10 A Address [9:0] $end
$upscope $end
$scope module mux_alu $end
$var wire 8 B D0 [7:0] $end
$var wire 8 C D1 [7:0] $end
$var wire 1 ' s $end
$var wire 8 D Y [7:0] $end
$upscope $end
$scope module mux_bc $end
$var wire 4 E D0 [3:0] $end
$var wire 4 F D1 [3:0] $end
$var wire 1 ' s $end
$var wire 4 G Y [3:0] $end
$upscope $end
$scope module mux_pc $end
$var wire 10 H D0 [9:0] $end
$var wire 1 & s $end
$var wire 10 I Y [9:0] $end
$var wire 10 J D1 [9:0] $end
$upscope $end
$scope module pc $end
$var wire 10 K D [9:0] $end
$var wire 1 $ clk $end
$var wire 1 % reset $end
$var reg 10 L Q [9:0] $end
$upscope $end
$scope module sumador $end
$var wire 10 M A [9:0] $end
$var wire 10 N B [9:0] $end
$var wire 10 O Y [9:0] $end
$upscope $end
$scope module zero_flag $end
$var wire 1 ) carga $end
$var wire 1 $ clk $end
$var wire 1 + d $end
$var wire 1 % reset $end
$var reg 1 ! q $end
$upscope $end
$upscope $end
$upscope $end
$scope module microc_tb $end
$scope module uut $end
$scope module banco_registros $end
$var reg 8 P \R[1] [7:0] $end
$upscope $end
$upscope $end
$upscope $end
$scope module microc_tb $end
$scope module uut $end
$scope module banco_registros $end
$var reg 8 Q \R[2] [7:0] $end
$upscope $end
$upscope $end
$upscope $end
$scope module microc_tb $end
$scope module uut $end
$scope module banco_registros $end
$var reg 8 R \R[3] [7:0] $end
$upscope $end
$upscope $end
$upscope $end
$enddefinitions $end
#0
$dumpvars
bx R
bx Q
bx P
b1 O
b1 N
b0 M
b0 L
b0x1 K
b1 J
b0x1 I
b11 H
b0xx G
b11 F
b0 E
b0 D
b0 C
b0 B
b0 A
b100000000000011 @
b0xx ?
b0 >
bx =
bx <
b11 ;
b0 :
bx 9
b0 8
bx 7
bx 6
b10000 5
b100000000000011 4
b0xx 3
b0 2
b0x1 1
b0 0
b0 /
bx .
b1 -
bx ,
x+
bx *
x)
x(
x'
x&
1%
1$
bx #
b10000 "
0!
$end
#500
0%
#1500
b0 .
b0 7
b0 =
1+
b0 ,
b0 9
b0 <
b11 1
b11 I
b11 K
b0 3
b0 ?
b0 G
b0 #
b0 *
b0 6
0&
0'
0(
0)
0$
#3000
b1 1
b1 I
b1 K
b100 "
b100 5
b1 F
b1 ;
b1 H
b100 -
b100 J
b100 O
b1000000000001 4
b1000000000001 @
b11 0
b11 A
b11 L
b11 M
1$
#4500
bx .
bx 7
bx =
b100 1
b100 I
b100 K
b1 3
b1 ?
b1 G
0$
1&
1'
1(
#6000
0+
b10 ,
b10 9
b10 <
b10 2
b10 8
b10 D
b10 3
b10 ?
b10 G
bx .
bx 7
bx =
b101 1
b101 I
b101 K
b10 C
b10 F
b10 E
b10 ;
b100010 H
b0 P
b101 -
b101 J
b101 O
b1000000100010 4
b1000000100010 @
b100 0
b100 A
b100 L
b100 M
1$
#7500
0$
#9000
b11 ,
b11 9
b11 <
b11 2
b11 8
b11 D
b11 3
b11 ?
b11 G
bx .
bx 7
bx =
b110 1
b110 I
b110 K
b11 C
b11 F
b11 E
b11 ;
b110011 H
b10 Q
b110 -
b110 J
b110 O
b1000000110011 4
b1000000110011 @
b101 0
b101 A
b101 L
b101 M
1$
#10500
0$
#12000
b10010 ,
b10010 9
b10010 <
b10010 2
b10010 8
b10010 D
b0 3
b0 ?
b0 G
b0 .
b0 7
b0 =
b111 1
b111 I
b111 K
b101100 "
b101100 5
b10010 C
b0 F
b10 E
b0 ;
b1 :
b100100000 H
b11 R
b111 -
b111 J
b111 O
b1011000100100000 4
b1011000100100000 @
b110 0
b110 A
b110 L
b110 M
1$
#13500
b10 .
b10 7
b10 =
0+
b11111110 ,
b11111110 9
b11111110 <
b0 2
b0 8
b0 D
b10 3
b10 ?
b10 G
0$
b11 #
b11 *
b11 6
0'
1)
#15000
x+
bx ,
bx 9
bx <
b0 .
b0 7
b0 =
bx 2
bx 8
bx D
b0 3
b0 ?
b0 G
bx /
bx >
bx B
b1000 1
b1000 I
b1000 K
b10010 "
b10010 5
b10000000 C
b1100 F
b0 E
b1100 ;
b1000 :
b1100 H
b1000 -
b1000 J
b1000 O
b100100000001100 4
b100100000001100 @
b111 0
b111 A
b111 L
b111 M
1$
#16500
0$
b0 #
b0 *
b0 6
0(
#18000
0+
b11 ,
b11 9
b11 <
b11 .
b11 7
b11 =
b11 2
b11 8
b11 D
b11 3
b11 ?
b11 G
b11 /
b11 >
b11 B
b1001 1
b1001 I
b1001 K
b101000 "
b101000 5
b110011 C
b11 F
b11 E
b11 ;
b11 :
b1100110011 H
b1001 -
b1001 J
b1001 O
b1010001100110011 4
b1010001100110011 @
b1000 0
b1000 A
b1000 L
b1000 M
x!
1$
#19500
b110 ,
b110 9
b110 <
0$
b10 #
b10 *
b10 6
1(
#21000
1+
b0 2
b0 8
b0 D
b0 ,
b0 9
b0 <
b1 3
b1 ?
b1 G
b0 /
b0 >
b0 B
b0 .
b0 7
b0 =
b1010 1
b1010 I
b1010 K
b1 C
b1 F
b1 E
b1 ;
b0 :
b10001 H
b110 R
0!
b1010 -
b1010 J
b1010 O
b1010000000010001 4
b1010000000010001 @
b1001 0
b1001 A
b1001 L
b1001 M
1$
#22500
0+
b1 ,
b1 9
b1 <
b1 2
b1 8
b1 D
0$
1'
#24000
1+
b0 ,
b0 9
b0 <
b0 2
b0 8
b0 D
b0 3
b0 ?
b0 G
b0 .
b0 7
b0 =
b1011 1
b1011 I
b1011 K
b0 "
b0 5
b0 C
b0 F
b0 E
b0 ;
b0 H
b1 P
b1011 -
b1011 J
b1011 O
b0 4
b0 @
b1010 0
b1010 A
b1010 L
b1010 M
1$
#25500
0$
b0 #
b0 *
b0 6
0'
0(
0)
#27000
b1100 1
b1100 I
b1100 K
b10000 "
b10000 5
b110 F
b110 ;
b110 H
b1100 -
b1100 J
b1100 O
b100000000000110 4
b100000000000110 @
b1011 0
b1011 A
b1011 L
b1011 M
1$
#28500
b110 1
b110 I
b110 K
0$
0&
#30000
0+
b1 ,
b1 9
b1 <
b10 .
b10 7
b10 =
b1 2
b1 8
b1 D
b10 3
b10 ?
b10 G
b1 /
b1 >
b1 B
b100100000 1
b100100000 I
b100100000 K
b101100 "
b101100 5
b10010 C
b0 F
b10 E
b0 ;
b1 :
b100100000 H
b111 -
b111 J
b111 O
b1011000100100000 4
b1011000100100000 @
b110 0
b110 A
b110 L
b110 M
1$
#31500
b11111111 ,
b11111111 9
b11111111 <
b111 1
b111 I
b111 K
0$
b11 #
b11 *
b11 6
1&
1(
1)
#33000
x+
bx ,
bx 9
bx <
b0 .
b0 7
b0 =
bx 2
bx 8
bx D
b0 3
b0 ?
b0 G
bx /
bx >
bx B
b1000 1
b1000 I
b1000 K
b10010 "
b10010 5
b10000000 C
b1100 F
b0 E
b1100 ;
b1000 :
b1100 H
b1000 -
b1000 J
b1000 O
b100100000001100 4
b100100000001100 @
b111 0
b111 A
b111 L
b111 M
1$
#34500
0$
b0 #
b0 *
b0 6
0(
#36000
0+
b110 ,
b110 9
b110 <
b110 .
b110 7
b110 =
b110 2
b110 8
b110 D
b11 3
b11 ?
b11 G
b110 /
b110 >
b110 B
b1001 1
b1001 I
b1001 K
b101000 "
b101000 5
b110011 C
b11 F
b11 E
b11 ;
b11 :
b1100110011 H
b1001 -
b1001 J
b1001 O
b1010001100110011 4
b1010001100110011 @
b1000 0
b1000 A
b1000 L
b1000 M
x!
1$
#37500
b1100 ,
b1100 9
b1100 <
0$
b10 #
b10 *
b10 6
1(
#39000
b0 2
b0 8
b0 D
b1 ,
b1 9
b1 <
b1 3
b1 ?
b1 G
b0 /
b0 >
b0 B
b1 .
b1 7
b1 =
b1010 1
b1010 I
b1010 K
b1 C
b1 F
b1 E
b1 ;
b0 :
b10001 H
b1100 R
0!
b1010 -
b1010 J
b1010 O
b1010000000010001 4
b1010000000010001 @
b1001 0
b1001 A
b1001 L
b1001 M
1$
#40500
b10 ,
b10 9
b10 <
b1 2
b1 8
b1 D
0$
1'
#42000
1+
b0 ,
b0 9
b0 <
b0 2
b0 8
b0 D
b0 3
b0 ?
b0 G
b0 .
b0 7
b0 =
b1011 1
b1011 I
b1011 K
b0 "
b0 5
b0 C
b0 F
b0 E
b0 ;
b0 H
b10 P
b1011 -
b1011 J
b1011 O
b0 4
b0 @
b1010 0
b1010 A
b1010 L
b1010 M
1$
#43500
0$
b0 #
b0 *
b0 6
0'
0(
0)
#45000
b1100 1
b1100 I
b1100 K
b10000 "
b10000 5
b110 F
b110 ;
b110 H
b1100 -
b1100 J
b1100 O
b100000000000110 4
b100000000000110 @
b1011 0
b1011 A
b1011 L
b1011 M
1$
#46500
b110 1
b110 I
b110 K
0$
0&
#48000
0+
b10 ,
b10 9
b10 <
b10 .
b10 7
b10 =
b10 2
b10 8
b10 D
b10 3
b10 ?
b10 G
b10 /
b10 >
b10 B
b100100000 1
b100100000 I
b100100000 K
b101100 "
b101100 5
b10010 C
b0 F
b10 E
b0 ;
b1 :
b100100000 H
b111 -
b111 J
b111 O
b1011000100100000 4
b1011000100100000 @
b110 0
b110 A
b110 L
b110 M
1$
#49500
1+
b0 ,
b0 9
b0 <
b111 1
b111 I
b111 K
0$
b11 #
b11 *
b11 6
1&
1(
1)
#51000
x+
bx ,
bx 9
bx <
b0 .
b0 7
b0 =
bx 2
bx 8
bx D
b0 3
b0 ?
b0 G
bx /
bx >
bx B
b1000 1
b1000 I
b1000 K
b10010 "
b10010 5
b10000000 C
b1100 F
b0 E
b1100 ;
b1000 :
b1100 H
1!
b1000 -
b1000 J
b1000 O
b100100000001100 4
b100100000001100 @
b111 0
b111 A
b111 L
b111 M
1$
#52500
b1100 1
b1100 I
b1100 K
0$
b0 #
b0 *
b0 6
0&
0(
#54000
1+
b0 ,
b0 9
b0 <
b0 2
b0 8
b0 D
b0 /
b0 >
b0 B
b10000 "
b10000 5
b0 C
b0 :
b1101 -
b1101 J
b1101 O
b100000000001100 4
b100000000001100 @
b1100 0
b1100 A
b1100 L
b1100 M
x!
1$
#55500
0$
0)
